poetry_snakemake_plugin/__init__.py
poetry_snakemake_plugin/common.py
poetry_snakemake_plugin/executor_plugins.py
poetry_snakemake_plugin/report_plugins.py
poetry_snakemake_plugin/software_deployment_plugins.py
poetry_snakemake_plugin/storage_plugins.py
poetry_snakemake_plugin/templates/ci.yml.j2
poetry_snakemake_plugin/templates/conventional_prs.yml.j2
poetry_snakemake_plugin/templates/executor-plugins/init.py
poetry_snakemake_plugin/templates/executor-plugins/tests.py.j2
poetry_snakemake_plugin/templates/release_please.yml.j2
poetry_snakemake_plugin/templates/report-plugins/init.py
poetry_snakemake_plugin/templates/report-plugins/tests.py
poetry_snakemake_plugin/templates/setup.cfg.j2
poetry_snakemake_plugin/templates/software-deployment-plugins/init.py
poetry_snakemake_plugin/templates/software-deployment-plugins/tests.py
poetry_snakemake_plugin/templates/storage-plugins/init.py
poetry_snakemake_plugin/templates/storage-plugins/tests.py
poetry_snakemake_plugin-0.8.1.dist-info/METADATA
poetry_snakemake_plugin-0.8.1.dist-info/WHEEL
poetry_snakemake_plugin-0.8.1.dist-info/entry_points.txt
poetry_snakemake_plugin-0.8.1.dist-info/RECORD
