Metadata-Version: 2.3
Name: poetry-snakemake-plugin
Version: 0.8.1
Summary: A plugin for poetry that adds Snakemake-specific functionality.
Author: Johannes Koester
Author-email: johannes.koester@uni-due.de
Requires-Python: >=3.9.1,<4.0
Classifier: Programming Language :: Python :: 3
Classifier: Programming Language :: Python :: 3.10
Classifier: Programming Language :: Python :: 3.11
Classifier: Programming Language :: Python :: 3.12
Classifier: Programming Language :: Python :: 3.13
Requires-Dist: cleo (>=2.0.1,<3.0.0)
Requires-Dist: jinja2 (>=3.1.2,<4.0.0)
Requires-Dist: poetry (>=2.0,<3.0)
Requires-Dist: toml (>=0.10.2,<0.11.0)
